setup.py
ctemplate/__init__.py
django_ctemplate.egg-info/PKG-INFO
django_ctemplate.egg-info/SOURCES.txt
django_ctemplate.egg-info/dependency_links.txt
django_ctemplate.egg-info/requires.txt
django_ctemplate.egg-info/top_level.txt