Metadata-Version: 1.0
Name: django-ctemplate
Version: 2.0.2
Summary: Compile Django templates to C
Home-page: https://chris-lamb.co.uk/projects/django-ctemplate
Author: Chris Lamb
Author-email: chris@chris-lamb.co.uk
License: UNKNOWN
Platform: UNKNOWN
